bootstrap.py
buildout.cfg
setup.py
docs/HISTORY.txt
src/megrok/__init__.py
src/megrok.z3cform.layout.egg-info/PKG-INFO
src/megrok.z3cform.layout.egg-info/SOURCES.txt
src/megrok.z3cform.layout.egg-info/dependency_links.txt
src/megrok.z3cform.layout.egg-info/entry_points.txt
src/megrok.z3cform.layout.egg-info/namespace_packages.txt
src/megrok.z3cform.layout.egg-info/not-zip-safe
src/megrok.z3cform.layout.egg-info/requires.txt
src/megrok.z3cform.layout.egg-info/top_level.txt
src/megrok/z3cform/__init__.py
src/megrok/z3cform/layout/README.txt
src/megrok/z3cform/layout/__init__.py
src/megrok/z3cform/layout/configure.zcml
src/megrok/z3cform/layout/interfaces.py
src/megrok/z3cform/layout/views.py
src/megrok/z3cform/layout/ftests/__init__.py
src/megrok/z3cform/layout/ftests/ftesting.zcml
src/megrok/z3cform/layout/ftests/test_all.py
src/megrok/z3cform/layout/views_templates/simpleform.pt