Metadata-Version: 1.0
Name: megrok.z3cform.layout
Version: 0.2.1
Summary: Generic templates for megrok.z3cform.base
Home-page: UNKNOWN
Author: Souheil Chelfouh
Author-email: trollfot@gmail.com
License: GPL
Keywords: Grok Form Templates Layout
Platform: UNKNOWN
Classifier: Programming Language :: Python
Classifier: Topic :: Software Development :: Libraries :: Python Modules
